LICENSE
MANIFEST.in
README.rst
lazy_string.py
setup.py
lazy_string.egg-info/PKG-INFO
lazy_string.egg-info/SOURCES.txt
lazy_string.egg-info/dependency_links.txt
lazy_string.egg-info/top_level.txt
lazy_string.egg-info/zip-safe