Metadata-Version: 2.1
Name: lazy-string
Version: 1.0.0
Summary: Python library for defining strings with delayed evaluation
Home-page: https://github.com/oblalex/lazy-string/tree/v1.0.0
Author: Oleksandr Oblovatnyi
Author-email: oblovatniy@gmail.com
License: MIT
Keywords: lazy,string,strings,lazy-evaluation,library,libraries
Platform: UNKNOWN
Classifier: Development Status :: 5 - Production/Stable
Classifier: Intended Audience :: Developers
Classifier: License :: OSI Approved :: MIT License
Classifier: Natural Language :: English
Classifier: Operating System :: MacOS :: MacOS X
Classifier: Operating System :: Microsoft :: Windows
Classifier: Operating System :: POSIX
Classifier: Programming Language :: Python :: 3
Classifier: Topic :: Software Development :: Libraries
Requires-Python: >=3.7
